dataicer/__init__.py
dataicer/_base_archive.py
dataicer/_core.py
dataicer/_dir_archive.py
dataicer/_errors.py
dataicer/_pip.py
dataicer/_utils.py
dataicer/_version.py
dataicer/plugins/__init__.py
dataicer/plugins/file.py
dataicer/plugins/numpy.py
dataicer/plugins/pandas.py
dataicer/plugins/xarray.py
dataicer-0.2.1.dist-info/LICENSE
dataicer-0.2.1.dist-info/METADATA
dataicer-0.2.1.dist-info/WHEEL
dataicer-0.2.1.dist-info/top_level.txt
dataicer-0.2.1.dist-info/RECORD
