Metadata-Version: 2.1
Name: dataicer
Version: 0.2.1
Summary: Ice (save) your data and high level objects for use later.
Home-page: https://github.com/trhallam/dataicer
Author-email: trhallam@gmail.com
License: MIT
Platform: UNKNOWN
Requires-Python: >=3.8
License-File: LICENSE
Requires-Dist: jsonpickle
Provides-Extra: test
Requires-Dist: pytest ; extra == 'test'
Requires-Dist: pytest-cov ; extra == 'test'
Requires-Dist: pandas ; extra == 'test'
Requires-Dist: numpy ; extra == 'test'
Requires-Dist: xarray ; extra == 'test'
Requires-Dist: h5netcdf ; extra == 'test'
Requires-Dist: tables ; extra == 'test'
